ledgerautosync/__init__.py
ledgerautosync/cli.py
ledgerautosync/converter.py
ledgerautosync/ledgerwrap.py
ledgerautosync/plugins.py
ledgerautosync/sync.py
ledger_autosync-1.2.0.dist-info/LICENSE
ledger_autosync-1.2.0.dist-info/METADATA
ledger_autosync-1.2.0.dist-info/WHEEL
ledger_autosync-1.2.0.dist-info/entry_points.txt
ledger_autosync-1.2.0.dist-info/RECORD
