Metadata-Version: 2.1
Name: ledger-autosync
Version: 1.2.0
Summary: Automatically sync your bank's data with ledger
Home-page: https://github.com/egh/ledger-autosync
License: GPLv3
Keywords: ledger,accounting
Author: Erik Hetzner
Author-email: egh@e6h.org
Requires-Python: >=3.8
Classifier: Development Status :: 5 - Production/Stable
Classifier: Intended Audience :: End Users/Desktop
Classifier: License :: Other/Proprietary License
Classifier: Operating System :: OS Independent
Classifier: Programming Language :: Python :: 3
Classifier: Programming Language :: Python :: 3.8
Classifier: Programming Language :: Python :: 3.9
Classifier: Programming Language :: Python :: 3.10
Classifier: Programming Language :: Python :: 3.11
Classifier: Programming Language :: Python :: 3.12
Classifier: Topic :: Office/Business :: Financial
Classifier: Topic :: Office/Business :: Financial :: Accounting
Classifier: Topic :: Office/Business :: Financial :: Investment
Requires-Dist: lxml
Requires-Dist: ofxclient
Requires-Dist: ofxparse
Project-URL: Repository, https://github.com/egh/ledger-autosync
